Workbook

Sheet BOM
A1: BOBBY v2.0 — BILL OF MATERIALS (BOM)
A2: Hardware Architecture & Components Specification | Target Cost: 15€–30€ production (10k units)
A4: Ref | B4: Category | C4: Component / Description | D4: Manufacturer | E4: Mfr Part # | F4: LCSC # | G4: Alt. Source | H4: Package | I4: Qty | J4: Unit Cost @1k (€) | K4: Unit Cost @10k (€) | L4: Ext. Cost @1k (€) | M4: Ext. Cost @10k (€) | N4: Notes
A5: U1 | B5: SOC | C5: ESP32-S3-WROOM-2 Module 16MB Flash / 8MB PSRAM | D5: Espressif | E5: ESP32-S3-WROOM-2-N16R8 | F5: C2913202 | G5: Mouser 356-ESP32S3WROOM2N16 | H5: SMD Module | I5: 1 | J5: 4.2 | K5: 3.5 | L5: =I5*J5 -> 4.2 | M5: =I5*K5 -> 3.5 | N5: Main MCU+WiFi+BLE. Xtensa LX7 240MHz dual core.
A6: U2 | B6: AUDIO | C6: INMP441 I2S MEMS Microphone LEFT | D6: TDK InvenSense | E6: INMP441ACEZ-T | F6: C3368792 | G6: Digi-Key 828-INMP441ACEZ-T | H6: SMD 3.76×4.72mm | I6: 1 | J6: 1.1 | K6: 0.85 | L6: =I6*J6 -> 1.1 | M6: =I6*K6 -> 0.85 | N6: Left channel. L/R pin → GND.
A7: U3 | B7: AUDIO | C7: INMP441 I2S MEMS Microphone RIGHT | D7: TDK InvenSense | E7: INMP441ACEZ-T | F7: C3368792 | G7: Digi-Key 828-INMP441ACEZ-T | H7: SMD 3.76×4.72mm | I7: 1 | J7: 1.1 | K7: 0.85 | L7: =I7*J7 -> 1.1 | M7: =I7*K7 -> 0.85 | N7: Right channel. L/R pin → VDD.
A8: U6 | B8: AUDIO | C8: MAX98357A I2S Class-D Amplifier 3W | D8: Maxim/ADI | E8: MAX98357AEWL+T | F8: C2655602 | G8: Mouser 700-MAX98357AEWL | H8: TQFN-16 3×3mm | I8: 1 | J8: 1.5 | K8: 1.2 | L8: =I8*J8 -> 1.5 | M8: =I8*K8 -> 1.2 | N8: 9dB gain (SD=GND). LC filter required.
A9: SP1 | B9: AUDIO | C9: Speaker 3W 4Ω 28mm | D9: KEPO | E9: SP0826F-1 or equiv. | F9: — | G9: AliExpress / Mouser | H9: Ø28mm or 36mm | I9: 1 | J9: 0.9 | K9: 0.6 | L9: =I9*J9 -> 0.9 | M9: =I9*K9 -> 0.6 | N9: 87 dB SPL @ 1W/1m. f0≈650Hz.
A10: L1 | B10: AUDIO | C10: Inductor 2.2µH SMD (Class-D filter) | D10: Murata | E10: LQM21FN2R2NGC | F10: C493614 | G10: LCSC | H10: 0805 | I10: 2 | J10: 0.12 | K10: 0.09 | L10: =I10*J10 -> 0.24 | M10: =I10*K10 -> 0.18 | N10: Isat≥1A. LC low-pass filter MAX98357A output.
A11: C_LC | B11: AUDIO | C11: Capacitor 220nF X5R SMD (LC filter) | D11: Yageo | E11: CC0805KRX5R9BB224 | F11: C49678 | G11: LCSC | H11: 0805 | I11: 2 | J11: 0.04 | K11: 0.03 | L11: =I11*J11 -> 0.08 | M11: =I11*K11 -> 0.06 | N11: Class-D output EMI filter.
A12: U7 | B12: CAMERA | C12: OV2640 Camera Module 2MP | D12: OmniVision | E12: OV2640-PLCC28 | F12: C16332 | G12: Mouser / AliExpress | H12: PLCC-28 + FPC | I12: 1 | J12: 3.2 | K12: 2.5 | L12: =I12*J12 -> 3.2 | M12: =I12*K12 -> 2.5 | N12: QVGA 30fps, DVP 8-bit. Facial recognition.
A13: LDO_CAM | B13: CAMERA | C13: LDO 2.8V 300mA (OV2640 AVDD) | D13: Diodes Inc. | E13: AMS1117-2.8 | F13: C6186 | G13: LCSC | H13: SOT-223 | I13: 1 | J13: 0.12 | K13: 0.09 | L13: =I13*J13 -> 0.12 | M13: =I13*K13 -> 0.09 | N13: OV2640 analog power supply.
A14: U8 | B14: DISPLAY | C14: GC9A01A Round LCD 240×240 1.28" | D14: Galaxycore | E14: GC9A01A | F14: C3045309 | G14: AliExpress module | H14: 1.28" IPS FPC | I14: 1 | J14: 2.4 | K14: 1.8 | L14: =I14*J14 -> 2.4 | M14: =I14*K14 -> 1.8 | N14: SPI 40MHz. 60Hz. 160° view. Backlight 40mA.
A15: Q1 | B15: DISPLAY | C15: N-MOSFET Si2302 (LCD backlight) | D15: Vishay | E15: Si2302 | F15: C11853 | G15: LCSC | H15: SOT-23 | I15: 1 | J15: 0.05 | K15: 0.04 | L15: =I15*J15 -> 0.05 | M15: =I15*K15 -> 0.04 | N15: PWM backlight control GPIO16.
A16: U4 | B16: POWER | C16: TP4056 Li-ion Charger 1A + DW01A protection | D16: TOPPOWER | E16: TP4056 | F16: C16581 | G16: LCSC | H16: SOP-8 | I16: 1 | J16: 0.2 | K16: 0.15 | L16: =I16*J16 -> 0.2 | M16: =I16*K16 -> 0.15 | N16: 500mA charge (R_PROG=2kΩ). DW01A OVP/UVP/OCP.
... A36: MISC | B36: ASSEMBLY | C36: Miscellaneous (screws M2, gasket, label, packaging) | D36: — | E36: — | F36: — | G36: Local | H36: — | I36: 1 | J36: 1.2 | K36: 0.8 | L36: =I36*J36 -> 1.2 | M36: =I36*K36 -> 0.8 | N36: IP40 gasket USB-C. Assembly hardware.
A37: TOTAL BOM COST (per unit) | L37: =SUM(L5:L36) -> 30.71 | M37: =SUM(M5:M36) -> 23.49

Sheet Cost Summary
A1: BOBBY v2.0 — COST SUMMARY
A2: BOM Cost Analysis by Category and Volume
A4: Category | B4: Cost @1k (€) | C4: Cost @10k (€) | D4: % of BOM @10k
A5: SOC | B5: =SUMIF(BOM!B:B,A5,BOM!L:L) -> 4.2 | C5: =SUMIF(BOM!B:B,A5,BOM!M:M) -> 3.5 | D5: =IFERROR(C5/C14,0) -> 0.14899957
A6: AUDIO | B6: =SUMIF(BOM!B:B,A6,BOM!L:L) -> 4.92 | C6: =SUMIF(BOM!B:B,A6,BOM!M:M) -> 3.74 | D6: =IFERROR(C6/C14,0) -> 0.15921669
A7: CAMERA | B7: =SUMIF(BOM!B:B,A7,BOM!L:L) -> 3.32 | C7: =SUMIF(BOM!B:B,A7,BOM!M:M) -> 2.59 | D7: =IFERROR(C7/C14,0) -> 0.11025968
A8: DISPLAY | B8: =SUMIF(BOM!B:B,A8,BOM!L:L) -> 2.45 | C8: =SUMIF(BOM!B:B,A8,BOM!M:M) -> 1.84 | D8: =IFERROR(C8/C14,0) -> 0.078331205
A9: POWER | B9: =SUMIF(BOM!B:B,A9,BOM!L:L) -> 6.89 | C9: =SUMIF(BOM!B:B,A9,BOM!M:M) -> 5.67 | D9: =IFERROR(C9/C14,0) -> 0.24137931
A10: CONNECTIVITY | B10: =SUMIF(BOM!B:B,A10,BOM!L:L) -> 1.48 | C10: =SUMIF(BOM!B:B,A10,BOM!M:M) -> 1.07 | D10: =IFERROR(C10/C14,0) -> 0.045551298
A11: UI | B11: =SUMIF(BOM!B:B,A11,BOM!L:L) -> 0.36 | C11: =SUMIF(BOM!B:B,A11,BOM!M:M) -> 0.25 | D11: =IFERROR(C11/C14,0) -> 0.010642827
A12: MECHANICAL | B12: =SUMIF(BOM!B:B,A12,BOM!L:L) -> 5.15 | C12: =SUMIF(BOM!B:B,A12,BOM!M:M) -> 3.45 | D12: =IFERROR(C12/C14,0) -> 0.14687101
A13: ASSEMBLY | B13: =SUMIF(BOM!B:B,A13,BOM!L:L) -> 1.94 | C13: =SUMIF(BOM!B:B,A13,BOM!M:M) -> 1.38 | D13: =IFERROR(C13/C14,0) -> 0.058748404
A14: TOTAL BOM (components only) | B14: =SUM(B5:B13) -> 30.71 | C14: =SUM(C5:C13) -> 23.49 | D14: 100.0%
A16: FULLY-LOADED UNIT COST BREAKDOWN
A17: BOM Components | B17: =B14 -> 30.71 | C17: =C14 -> 23.49
A18: PCB Assembly (PCBA) | B18: 5 | C18: 3.5
A19: End-of-Line Test (EOL) | B19: 1.5 | C19: 1
A20: Logistics & Packaging | B20: 1.2 | C20: 0.8
A21: Mold Amortization (50k pcs) | B21: 0.25 | C21: 0.1
A22: Warranty Reserve (5%) | B22: =B17*0.05 -> 1.5355 | C22: =C17*0.05 -> 1.1745
A23: TOTAL PRODUCTION COST / UNIT | B23: =SUM(B17:B22) -> 40.1955 | C23: =SUM(C17:C22) -> 30.0645
A24: ✅ Target: ≤ 30€/unit @ 10k — MVP within budget. Retail price target: 79€–99€ (3.0–3.5× BOM margin)

Sheet Suppliers
A1: BOBBY v2.0 — SUPPLIER DIRECTORY
A2: Supplier | B2: URL | C2: Category | D2: Min Order | E2: Lead Time | F2: Notes
A3: LCSC | B3: lcsc.com | C3: All components | D3: 1 pcs | E3: 3–5 days | F3: Best price on Chinese components. Integrates with JLCPCB PCBA.
A4: JLCPCB | B4: jlcpcb.com | C4: PCB + PCBA | D4: 5 pcs | E4: 5–10 days | F4: Best value for <5k PCB orders. PCBA for SMT components.
A5: Mouser | B5: mouser.com | C5: All components | D5: 1 pcs | E5: 2–3 days | F5: Western distributor. Higher price but global stock.
A6: Digi-Key | B6: digikey.com | C6: All components | D6: 1 pcs | E6: 2–3 days | F6: Reliable for samples and low volume. Good TI/ADI stock.
A7: AliExpress | B7: aliexpress.com | C7: Modules/screens | D7: 1 pcs | E7: 7–20 days | F7: Camera modules, LCD modules. Use for prototyping only.
A8: PCBWay | B8: pcbway.com | C8: PCB + PCBA | D8: 5 pcs | E8: 7–14 days | F8: Alternative to JLCPCB for larger production runs.
A9: MacroFab | B9: macrofab.com | C9: PCBA | D9: 10 pcs | E9: 14–21 days | F9: US-based PCBA. Higher cost but DFM support.
A10: OMH (Shenzhen) | B10: omhcn.com | C10: Enclosure (mold) | D10: 1k pcs | E10: 30–45 days | F10: ABS injection molding. ~5k€ for steel mold.
A11: Espressif | B11: espressif.com | C11: ESP32 SoCs | D11: 10 pcs | E11: 5–7 days | F11: Official distributor for ESP32-S3 modules.
A12: TDK InvenSense | B12: invensense.tdk.com | C12: MEMS Mics | D12: 100 pcs | E12: 10 days | F12: INMP441 official. Also via Mouser.
A13: Texas Instrum. | B13: ti.com | C13: PMIC (TPS63020) | D13: 1 pcs | E13: 3–5 days | F13: TI store for samples. Volume via Mouser/Digi-Key.
